spyq/__init__.py
spyq/cli.py
spyq/commands/__init__.py
spyq/commands/init.py
spyq/config.py
spyq/importhook.py
spyq/install.py
spyq/quality.py
spyq/setup_quality_guard.py
spyq/validator.py
spyq-0.1.32.dist-info/LICENSE
spyq-0.1.32.dist-info/METADATA
spyq-0.1.32.dist-info/WHEEL
spyq-0.1.32.dist-info/entry_points.txt
spyq-0.1.32.dist-info/RECORD
