Metadata-Version: 2.3
Name: spyq
Version: 0.1.32
Summary: SPYQ - Shell Python Quality Guard
License: Apache-2.0
Author: Tom Sapletta
Author-email: tom@sapletta.com
Requires-Python: >=3.8.1,<4.0.0
Classifier: License :: OSI Approved :: Apache Software License
Classifier: Programming Language :: Python :: 3
Classifier: Programming Language :: Python :: 3.9
Classifier: Programming Language :: Python :: 3.10
Classifier: Programming Language :: Python :: 3.11
Classifier: Programming Language :: Python :: 3.12
Classifier: Programming Language :: Python :: 3.13
Requires-Dist: click (>=8.1.7,<9.0.0)
